[
    {
        "title": "To Kill a Mockingbird",
        "isbn13": "9780061120084",
        "price": "$9.99",
        "image": "https://example.com/to-kill-a-mockingbird.jpg",
        "url": "https://example.com/to-kill-a-mockingbird"
    },
    {
        "title": "1984",
        "isbn13": "9780451524935",
        "price": "$8.99",
        "image": "https://example.com/1984.jpg",
        "url": "https://example.com/1984"
    },
    {
        "title": "The Great Gatsby",
        "isbn13": "9780743273565",
        "price": "$10.99",
        "image": "https://example.com/the-great-gatsby.jpg",
        "url": "https://example.com/the-great-gatsby"
    },
    {
        "title": "Pride and Prejudice",
        "isbn13": "9780141439518",
        "price": "$7.50",
        "image": "https://example.com/pride-and-prejudice.jpg",
        "url": "https://example.com/pride-and-prejudice"
    },
    {
        "title": "Harry Potter and the Sorcerer's Stone",
        "isbn13": "9780590353427",
        "price": "$12.99",
        "image": "https://example.com/harry-potter-and-the-sorcerers-stone.jpg",
        "url": "https://example.com/harry-potter-and-the-sorcerers-stone"
    },
    {
        "title": "The Hobbit",
        "isbn13": "9780345534835",
        "price": "$11.25",
        "image": "https://example.com/the-hobbit.jpg",
        "url": "https://example.com/the-hobbit"
    },
    {
        "title": "Lord of the Flies",
        "isbn13": "9780143124290",
        "price": "$8.99",
        "image": "https://example.com/lord-of-the-flies.jpg",
        "url": "https://example.com/lord-of-the-flies"
    },
    {
        "title": "The Catcher in the Rye",
        "isbn13": "9780316769488",
        "price": "$6.75",
        "image": "https://example.com/the-catcher-in-the-rye.jpg",
        "url": "https://example.com/the-catcher-in-the-rye"
    },
    {
        "title": "The Lord of the Rings",
        "isbn13": "9780544003415",
        "price": "$21.99",
        "image": "https://example.com/the-lord-of-the-rings.jpg",
        "url": "https://example.com/the-lord-of-the-rings"
    },
    {
        "title": "Animal Farm",
        "isbn13": "9780451526342",
        "price": "$7.99",
        "image": "https://example.com/animal-farm.jpg",
        "url": "https://example.com/animal-farm"
    },
    {
        "title": "Brave New World",
        "isbn13": "9780060850524",
        "price": "$9.25",
        "image": "https://example.com/brave-new-world.jpg",
        "url": "https://example.com/brave-new-world"
    },
    {
        "title": "The Da Vinci Code",
        "isbn13": "9780307474278",
        "price": "$11.99",
        "image": "https://example.com/the-da-vinci-code.jpg",
        "url": "https://example.com/the-da-vinci-code"
    },
    {
        "title": "The Alchemist",
        "isbn13": "9780062315007",
        "price": "$10.50",
        "image": "https://example.com/the-alchemist.jpg",
        "url": "https://example.com/the-alchemist"
    },
    {
        "title": "Gone with the Wind",
        "isbn13": "9780446675536",
        "price": "$13.75",
        "image": "https://example.com/gone-with-the-wind.jpg",
        "url": "https://example.com/gone-with-the-wind"
    },
    {
        "title": "The Hunger Games",
        "isbn13": "9780439023528",
        "price": "$9.99",
        "image": "https://example.com/the-hunger-games.jpg",
        "url": "https://example.com/the-hunger-games"
    },
    {
        "title": "The Road",
        "isbn13": "9780307387899",
        "price": "$8.25",
        "image": "https://example.com/the-road.jpg",
        "url": "https://example.com/the-road"
    },
    {
        "title": "The Chronicles of Narnia",
        "isbn13": "9780064404990",
        "price": "$19.99",
        "image": "https://example.com/the-chronicles-of-narnia.jpg",
        "url": "https://example.com/the-chronicles-of-narnia"
    },
    {
        "title": "Frankenstein",
        "isbn13": "9780141439471",
        "price": "$6.99",
        "image": "https://example.com/frankenstein.jpg",
        "url": "https://example.com/frankenstein"
    },
    {
        "title": "Moby-Dick",
        "isbn13": "9781853260087",
        "price": "$14.99",
        "image": "https://example.com/moby-dick.jpg",
        "url": "https://example.com/moby-dick"
    },
    {
        "title": "The Picture of Dorian Gray",
        "isbn13": "9780141439570",
        "price": "$8.50",
        "image": "https://example.com/the-picture-of-dorian-gray.jpg",
        "url": "https://example.com/the-picture-of-dorian-gray"
    },
    {
        "title": "Jane Eyre",
        "isbn13": "9780142437209",
        "price": "$7.99",
        "image": "https://example.com/jane-eyre.jpg",
        "url": "https://example.com/jane-eyre"
    }
]
